LICENSE
MANIFEST.in
README.rst
setup.py
django_csv_tests/__init__.py
django_csv_tests.egg-info/PKG-INFO
django_csv_tests.egg-info/SOURCES.txt
django_csv_tests.egg-info/dependency_links.txt
django_csv_tests.egg-info/requires.txt
django_csv_tests.egg-info/top_level.txt
django_csv_tests/tests/__init__.py
django_csv_tests/tests/manage.py
django_csv_tests/tests/test_settings.py
django_csv_tests/tests/urls.py
django_csv_tests/tests/templates/index.html
django_csv_tests/tests/test_app/__init__.py
django_csv_tests/tests/test_app/models.py
django_csv_tests/tests/test_app/tests.csv
django_csv_tests/tests/test_app/tests.py
django_csv_tests/tests/test_app/views.py