Metadata-Version: 1.0
Name: django-csv-tests
Version: 0.1.5
Summary: This allows you to use a spreadsheet to define Django units tests that make requests to the Django testing client.
Home-page: https://github.com/enricobarzetti/django_csv_tests
Author: Enrico Barzetti
Author-email: enricobarzetti@gmail.com
License: The MIT License
Keywords: django
Platform: OS Independent
